isort_gaussdb.py
isort_gaussdb-0.0.6.dist-info/METADATA
isort_gaussdb-0.0.6.dist-info/WHEEL
isort_gaussdb-0.0.6.dist-info/entry_points.txt
isort_gaussdb-0.0.6.dist-info/top_level.txt
isort_gaussdb-0.0.6.dist-info/RECORD
