Metadata-Version: 2.4
Name: isort-gaussdb
Version: 0.0.6
Summary: isort plug-in to sort imports by module length first
Author-email: Daniele Varrazzo <daniele.varrazzo@gmail.com>
Project-URL: Homepage, https://github.com/HuaweiCloudDeveloper/gaussdb-python/
Project-URL: Documentation, https://github.com/HuaweiCloudDeveloper/gaussdb-python/
Project-URL: Code, https://github.com/HuaweiCloudDeveloper/gaussdb-python/
Project-URL: Issue Tracker, https://github.com/HuaweiCloudDeveloper/gaussdb-python/issues
